apitoolkit_python/__init__.py
apitoolkit_python-0.1.5.dist-info/LICENSE
apitoolkit_python-0.1.5.dist-info/METADATA
apitoolkit_python-0.1.5.dist-info/WHEEL
apitoolkit_python-0.1.5.dist-info/top_level.txt
apitoolkit_python-0.1.5.dist-info/RECORD
