Metadata-Version: 2.1
Name: apitoolkit-python
Version: 0.1.5
Summary: A share python sdk for python web frameworks
Home-page: UNKNOWN
Author: APIToolkit
Author-email: hello@apitoolkit.io
License: UNKNOWN
Platform: UNKNOWN
License-File: LICENSE
Requires-Dist: httpx
Requires-Dist: jsonpath-ng
Requires-Dist: requests
